{
 "custom_fields": [
  {
   "_assign": null,
   "_comments": null,
   "_liked_by": null,
   "_user_tags": null,
   "allow_in_quick_entry": 0,
   "allow_on_submit": 0,
   "bold": 0,
   "collapsible": 0,
   "collapsible_depends_on": null,
   "columns": 0,
   "creation": "2020-09-06 09:28:07.395107",
   "default": null,
   "depends_on": null,
   "description": null,
   "docstatus": 0,
   "dt": "Quotation",
   "fetch_from": null,
   "fetch_if_empty": 0,
   "fieldname": "product_bundle_section_cf",
   "fieldtype": "Section Break",
   "hidden": 0,
   "hide_border": 0,
   "hide_days": 0,
   "hide_seconds": 0,
   "idx": 37,
   "ignore_user_permissions": 0,
   "ignore_xss_filter": 0,
   "in_global_search": 0,
   "in_list_view": 0,
   "in_preview": 0,
   "in_standard_filter": 0,
   "insert_after": "ignore_pricing_rule",
   "label": "",
   "length": 0,
   "mandatory_depends_on": null,
   "modified": "2020-09-06 09:28:07.395107",
   "modified_by": "Administrator",
   "name": "Quotation-product_bundle_section_cf",
   "no_copy": 0,
   "non_negative": 0,
   "options": null,
   "owner": "Administrator",
   "parent": null,
   "parentfield": null,
   "parenttype": null,
   "permlevel": 0,
   "precision": "",
   "print_hide": 0,
   "print_hide_if_no_value": 0,
   "print_width": null,
   "read_only": 0,
   "read_only_depends_on": null,
   "report_hide": 0,
   "reqd": 0,
   "search_index": 0,
   "translatable": 0,
   "unique": 0,
   "width": null
  },
  {
   "_assign": null,
   "_comments": null,
   "_liked_by": null,
   "_user_tags": null,
   "allow_in_quick_entry": 0,
   "allow_on_submit": 0,
   "bold": 0,
   "collapsible": 0,
   "collapsible_depends_on": null,
   "columns": 0,
   "creation": "2020-09-06 09:28:07.872998",
   "default": null,
   "depends_on": null,
   "description": null,
   "docstatus": 0,
   "dt": "Quotation",
   "fetch_from": null,
   "fetch_if_empty": 0,
   "fieldname": "product_bundle_item_cf",
   "fieldtype": "Link",
   "hidden": 0,
   "hide_border": 0,
   "hide_days": 0,
   "hide_seconds": 0,
   "idx": 38,
   "ignore_user_permissions": 0,
   "ignore_xss_filter": 0,
   "in_global_search": 0,
   "in_list_view": 0,
   "in_preview": 0,
   "in_standard_filter": 0,
   "insert_after": "product_bundle_section_cf",
   "label": "Product Bundle Item",
   "length": 0,
   "mandatory_depends_on": null,
   "modified": "2020-09-06 09:28:07.872998",
   "modified_by": "Administrator",
   "name": "Quotation-product_bundle_item_cf",
   "no_copy": 0,
   "non_negative": 0,
   "options": "Item",
   "owner": "Administrator",
   "parent": null,
   "parentfield": null,
   "parenttype": null,
   "permlevel": 0,
   "precision": "",
   "print_hide": 0,
   "print_hide_if_no_value": 0,
   "print_width": null,
   "read_only": 0,
   "read_only_depends_on": null,
   "report_hide": 0,
   "reqd": 0,
   "search_index": 0,
   "translatable": 0,
   "unique": 0,
   "width": null
  },
  {
   "_assign": null,
   "_comments": null,
   "_liked_by": null,
   "_user_tags": null,
   "allow_in_quick_entry": 0,
   "allow_on_submit": 0,
   "bold": 0,
   "collapsible": 0,
   "collapsible_depends_on": null,
   "columns": 0,
   "creation": "2020-09-06 09:28:08.758780",
   "default": null,
   "depends_on": null,
   "description": null,
   "docstatus": 0,
   "dt": "Quotation",
   "fetch_from": null,
   "fetch_if_empty": 0,
   "fieldname": "product_bundle_column_cf",
   "fieldtype": "Column Break",
   "hidden": 0,
   "hide_border": 0,
   "hide_days": 0,
   "hide_seconds": 0,
   "idx": 39,
   "ignore_user_permissions": 0,
   "ignore_xss_filter": 0,
   "in_global_search": 0,
   "in_list_view": 0,
   "in_preview": 0,
   "in_standard_filter": 0,
   "insert_after": "product_bundle_item_cf",
   "label": "",
   "length": 0,
   "mandatory_depends_on": null,
   "modified": "2020-09-06 09:28:08.758780",
   "modified_by": "Administrator",
   "name": "Quotation-product_bundle_column_cf",
   "no_copy": 0,
   "non_negative": 0,
   "options": null,
   "owner": "Administrator",
   "parent": null,
   "parentfield": null,
   "parenttype": null,
   "permlevel": 0,
   "precision": "",
   "print_hide": 0,
   "print_hide_if_no_value": 0,
   "print_width": null,
   "read_only": 0,
   "read_only_depends_on": null,
   "report_hide": 0,
   "reqd": 0,
   "search_index": 0,
   "translatable": 0,
   "unique": 0,
   "width": null
  },
  {
   "_assign": null,
   "_comments": null,
   "_liked_by": null,
   "_user_tags": null,
   "allow_in_quick_entry": 0,
   "allow_on_submit": 0,
   "bold": 0,
   "collapsible": 0,
   "collapsible_depends_on": null,
   "columns": 0,
   "creation": "2020-09-06 09:28:09.228723",
   "default": null,
   "depends_on": "",
   "description": null,
   "docstatus": 0,
   "dt": "Quotation",
   "fetch_from": null,
   "fetch_if_empty": 0,
   "fieldname": "create_product_bundle_cf",
   "fieldtype": "Button",
   "hidden": 0,
   "hide_border": 0,
   "hide_days": 0,
   "hide_seconds": 0,
   "idx": 40,
   "ignore_user_permissions": 0,
   "ignore_xss_filter": 0,
   "in_global_search": 0,
   "in_list_view": 0,
   "in_preview": 0,
   "in_standard_filter": 0,
   "insert_after": "product_bundle_column_cf",
   "label": "Create Product Bundle",
   "length": 0,
   "mandatory_depends_on": null,
   "modified": "2020-09-06 09:28:09.228723",
   "modified_by": "Administrator",
   "name": "Quotation-create_product_bundle_cf",
   "no_copy": 0,
   "non_negative": 0,
   "options": null,
   "owner": "Administrator",
   "parent": null,
   "parentfield": null,
   "parenttype": null,
   "permlevel": 0,
   "precision": "",
   "print_hide": 0,
   "print_hide_if_no_value": 0,
   "print_width": null,
   "read_only": 0,
   "read_only_depends_on": null,
   "report_hide": 0,
   "reqd": 0,
   "search_index": 0,
   "translatable": 0,
   "unique": 0,
   "width": null
  },
  {
   "_assign": null,
   "_comments": null,
   "_liked_by": null,
   "_user_tags": null,
   "allow_in_quick_entry": 0,
   "allow_on_submit": 0,
   "bold": 0,
   "collapsible": 0,
   "collapsible_depends_on": null,
   "columns": 0,
   "creation": "2021-11-25 17:17:41.710250",
   "default": null,
   "depends_on": null,
   "description": null,
   "docstatus": 0,
   "dt": "Quotation",
   "fetch_from": "sales_responsible_cf.full_name",
   "fetch_if_empty": 0,
   "fieldname": "sales_person_full_name_cf",
   "fieldtype": "Data",
   "hidden": 1,
   "hide_border": 0,
   "hide_days": 0,
   "hide_seconds": 0,
   "idx": 3,
   "ignore_user_permissions": 0,
   "ignore_xss_filter": 0,
   "in_global_search": 0,
   "in_list_view": 0,
   "in_preview": 0,
   "in_standard_filter": 0,
   "insert_after": "sales_responsible_cf",
   "label": "Sales Person Full Name",
   "length": 0,
   "mandatory_depends_on": null,
   "modified": "2021-11-25 17:17:41.710250",
   "modified_by": "Administrator",
   "name": "Quotation-sales_person_full_name_cf",
   "no_copy": 0,
   "non_negative": 0,
   "options": null,
   "owner": "Administrator",
   "parent": null,
   "parentfield": null,
   "parenttype": null,
   "permlevel": 0,
   "precision": "",
   "print_hide": 0,
   "print_hide_if_no_value": 0,
   "print_width": null,
   "read_only": 1,
   "read_only_depends_on": null,
   "report_hide": 0,
   "reqd": 0,
   "search_index": 0,
   "translatable": 0,
   "unique": 0,
   "width": null
  },
  {
   "_assign": null,
   "_comments": null,
   "_liked_by": null,
   "_user_tags": null,
   "allow_in_quick_entry": 0,
   "allow_on_submit": 0,
   "bold": 0,
   "collapsible": 0,
   "collapsible_depends_on": null,
   "columns": 0,
   "creation": "2021-11-25 17:17:42.891139",
   "default": null,
   "depends_on": null,
   "description": null,
   "docstatus": 0,
   "dt": "Quotation",
   "fetch_from": "sales_responsible_cf.mobile_no",
   "fetch_if_empty": 0,
   "fieldname": "sales_person_mobile_no_cf",
   "fieldtype": "Data",
   "hidden": 1,
   "hide_border": 0,
   "hide_days": 0,
   "hide_seconds": 0,
   "idx": 4,
   "ignore_user_permissions": 0,
   "ignore_xss_filter": 0,
   "in_global_search": 0,
   "in_list_view": 0,
   "in_preview": 0,
   "in_standard_filter": 0,
   "insert_after": "sales_person_full_name_cf",
   "label": "Sales Person Mobile No",
   "length": 0,
   "mandatory_depends_on": null,
   "modified": "2021-11-25 17:17:42.891139",
   "modified_by": "Administrator",
   "name": "Quotation-sales_person_mobile_no_cf",
   "no_copy": 0,
   "non_negative": 0,
   "options": null,
   "owner": "Administrator",
   "parent": null,
   "parentfield": null,
   "parenttype": null,
   "permlevel": 0,
   "precision": "",
   "print_hide": 0,
   "print_hide_if_no_value": 0,
   "print_width": null,
   "read_only": 1,
   "read_only_depends_on": null,
   "report_hide": 0,
   "reqd": 0,
   "search_index": 0,
   "translatable": 0,
   "unique": 0,
   "width": null
  },
  {
   "_assign": null,
   "_comments": null,
   "_liked_by": null,
   "_user_tags": null,
   "allow_in_quick_entry": 0,
   "allow_on_submit": 0,
   "bold": 0,
   "collapsible": 0,
   "collapsible_depends_on": null,
   "columns": 0,
   "creation": "2021-11-25 17:49:54.317418",
   "default": null,
   "depends_on": null,
   "description": null,
   "docstatus": 0,
   "dt": "Quotation",
   "fetch_from": "sales_responsible_cf.email_signature",
   "fetch_if_empty": 0,
   "fieldname": "sales_person_email_signature_cf",
   "fieldtype": "Data",
   "hidden": 0,
   "hide_border": 0,
   "hide_days": 0,
   "hide_seconds": 0,
   "idx": 5,
   "ignore_user_permissions": 0,
   "ignore_xss_filter": 0,
   "in_global_search": 0,
   "in_list_view": 0,
   "in_preview": 0,
   "in_standard_filter": 0,
   "insert_after": "sales_person_mobile_no_cf",
   "label": "Prepared By",
   "length": 0,
   "mandatory_depends_on": null,
   "modified": "2021-11-25 17:49:54.317418",
   "modified_by": "seo@amrutenergy.com",
   "name": "Quotation-sales_person_email_signature_cf",
   "no_copy": 0,
   "non_negative": 0,
   "options": null,
   "owner": "seo@amrutenergy.com",
   "parent": null,
   "parentfield": null,
   "parenttype": null,
   "permlevel": 0,
   "precision": "",
   "print_hide": 0,
   "print_hide_if_no_value": 0,
   "print_width": null,
   "read_only": 1,
   "read_only_depends_on": null,
   "report_hide": 0,
   "reqd": 0,
   "search_index": 0,
   "translatable": 0,
   "unique": 0,
   "width": null
  },
  {
   "_assign": null,
   "_comments": null,
   "_liked_by": null,
   "_user_tags": null,
   "allow_in_quick_entry": 0,
   "allow_on_submit": 0,
   "bold": 0,
   "collapsible": 0,
   "collapsible_depends_on": null,
   "columns": 0,
   "creation": "2021-12-11 18:25:55.775698",
   "default": null,
   "depends_on": null,
   "description": null,
   "docstatus": 0,
   "dt": "Quotation",
   "fetch_from": null,
   "fetch_if_empty": 0,
   "fieldname": "exempt_from_sales_tax",
   "fieldtype": "Check",
   "hidden": 0,
   "hide_border": 0,
   "hide_days": 0,
   "hide_seconds": 0,
   "idx": 61,
   "ignore_user_permissions": 0,
   "ignore_xss_filter": 0,
   "in_global_search": 0,
   "in_list_view": 0,
   "in_preview": 0,
   "in_standard_filter": 0,
   "insert_after": "taxes_and_charges",
   "label": "Is customer exempted from sales tax?",
   "length": 0,
   "mandatory_depends_on": null,
   "modified": "2021-12-11 18:25:55.775698",
   "modified_by": "amrutenergy@amrutenergy.com",
   "name": "Quotation-exempt_from_sales_tax",
   "no_copy": 0,
   "non_negative": 0,
   "options": null,
   "owner": "Administrator",
   "parent": null,
   "parentfield": null,
   "parenttype": null,
   "permlevel": 0,
   "precision": "",
   "print_hide": 0,
   "print_hide_if_no_value": 0,
   "print_width": null,
   "read_only": 0,
   "read_only_depends_on": null,
   "report_hide": 0,
   "reqd": 0,
   "search_index": 0,
   "translatable": 0,
   "unique": 0,
   "width": null
  },
  {
   "_assign": null,
   "_comments": null,
   "_liked_by": null,
   "_user_tags": null,
   "allow_in_quick_entry": 0,
   "allow_on_submit": 0,
   "bold": 0,
   "collapsible": 0,
   "collapsible_depends_on": null,
   "columns": 0,
   "creation": "2021-12-20 17:47:52.479209",
   "default": null,
   "depends_on": null,
   "description": null,
   "docstatus": 0,
   "dt": "Quotation",
   "fetch_from": null,
   "fetch_if_empty": 0,
   "fieldname": "sales_responsible_cf",
   "fieldtype": "Link",
   "hidden": 0,
   "hide_border": 0,
   "hide_days": 0,
   "hide_seconds": 0,
   "idx": 2,
   "ignore_user_permissions": 0,
   "ignore_xss_filter": 0,
   "in_global_search": 0,
   "in_list_view": 0,
   "in_preview": 0,
   "in_standard_filter": 0,
   "insert_after": "customer_section",
   "label": "Sales Person",
   "length": 0,
   "mandatory_depends_on": null,
   "modified": "2021-12-20 17:47:52.479209",
   "modified_by": "amrutenergy@amrutenergy.com",
   "name": "Quotation-sales_responsible_cf",
   "no_copy": 0,
   "non_negative": 0,
   "options": "User",
   "owner": "amrutenergy@amrutenergy.com",
   "parent": null,
   "parentfield": null,
   "parenttype": null,
   "permlevel": 0,
   "precision": "",
   "print_hide": 0,
   "print_hide_if_no_value": 0,
   "print_width": null,
   "read_only": 0,
   "read_only_depends_on": null,
   "report_hide": 0,
   "reqd": 0,
   "search_index": 0,
   "translatable": 0,
   "unique": 0,
   "width": null
  },
  {
   "_assign": null,
   "_comments": null,
   "_liked_by": null,
   "_user_tags": null,
   "allow_in_quick_entry": 0,
   "allow_on_submit": 0,
   "bold": 0,
   "collapsible": 0,
   "collapsible_depends_on": null,
   "columns": 0,
   "creation": "2022-02-28 10:40:35.066377",
   "default": null,
   "depends_on": null,
   "description": null,
   "docstatus": 0,
   "dt": "Quotation",
   "fetch_from": null,
   "fetch_if_empty": 0,
   "fieldname": "doc_pdf_url_cf",
   "fieldtype": "Data",
   "hidden": 0,
   "hide_border": 0,
   "hide_days": 0,
   "hide_seconds": 0,
   "idx": 112,
   "ignore_user_permissions": 0,
   "ignore_xss_filter": 0,
   "in_global_search": 0,
   "in_list_view": 0,
   "in_preview": 0,
   "in_standard_filter": 0,
   "insert_after": "lost_reasons",
   "label": "Doc Pdf Url",
   "length": 0,
   "mandatory_depends_on": null,
   "modified": "2022-02-28 10:40:35.066377",
   "modified_by": "Administrator",
   "name": "Quotation-doc_pdf_url_cf",
   "no_copy": 0,
   "non_negative": 0,
   "options": null,
   "owner": "Administrator",
   "parent": null,
   "parentfield": null,
   "parenttype": null,
   "permlevel": 0,
   "precision": "",
   "print_hide": 0,
   "print_hide_if_no_value": 0,
   "print_width": null,
   "read_only": 1,
   "read_only_depends_on": null,
   "report_hide": 0,
   "reqd": 0,
   "search_index": 0,
   "translatable": 0,
   "unique": 0,
   "width": null
  }
 ],
 "custom_perms": [],
 "doctype": "Quotation",
 "property_setters": [
  {
   "_assign": null,
   "_comments": null,
   "_liked_by": null,
   "_user_tags": null,
   "creation": "2020-08-25 01:03:42.039871",
   "default_value": null,
   "doc_type": "Quotation",
   "docstatus": 0,
   "doctype_or_field": "DocField",
   "field_name": "naming_series",
   "idx": 0,
   "modified": "2020-08-25 01:03:42.039871",
   "modified_by": "Administrator",
   "name": "Quotation-naming_series-options",
   "owner": "Administrator",
   "parent": null,
   "parentfield": null,
   "parenttype": null,
   "property": "options",
   "property_type": "Text",
   "row_name": null,
   "value": "SAL-QTN-.YYYY.-"
  },
  {
   "_assign": null,
   "_comments": null,
   "_liked_by": null,
   "_user_tags": null,
   "creation": "2020-08-12 17:17:36.182312",
   "default_value": null,
   "doc_type": "Quotation",
   "docstatus": 0,
   "doctype_or_field": "DocType",
   "field_name": null,
   "idx": 0,
   "modified": "2020-08-12 17:17:36.182312",
   "modified_by": "amrutenergy@amrutenergy.com",
   "name": "Quotation-default_print_format",
   "owner": "amrutenergy@amrutenergy.com",
   "parent": null,
   "parentfield": null,
   "parenttype": null,
   "property": "default_print_format",
   "property_type": "Data",
   "row_name": null,
   "value": "Quotation"
  },
  {
   "_assign": null,
   "_comments": null,
   "_liked_by": null,
   "_user_tags": null,
   "creation": "2020-06-23 11:44:42.733158",
   "default_value": null,
   "doc_type": "Quotation",
   "docstatus": 0,
   "doctype_or_field": "DocField",
   "field_name": "in_words",
   "idx": 0,
   "modified": "2020-06-23 11:44:42.733158",
   "modified_by": "amrutenergy@amrutenergy.com",
   "name": "Quotation-in_words-print_hide",
   "owner": "amrutenergy@amrutenergy.com",
   "parent": null,
   "parentfield": null,
   "parenttype": null,
   "property": "print_hide",
   "property_type": "Check",
   "row_name": null,
   "value": "0"
  },
  {
   "_assign": null,
   "_comments": null,
   "_liked_by": null,
   "_user_tags": null,
   "creation": "2020-06-23 11:44:42.577078",
   "default_value": null,
   "doc_type": "Quotation",
   "docstatus": 0,
   "doctype_or_field": "DocField",
   "field_name": "in_words",
   "idx": 0,
   "modified": "2020-06-23 11:44:42.577078",
   "modified_by": "amrutenergy@amrutenergy.com",
   "name": "Quotation-in_words-hidden",
   "owner": "amrutenergy@amrutenergy.com",
   "parent": null,
   "parentfield": null,
   "parenttype": null,
   "property": "hidden",
   "property_type": "Check",
   "row_name": null,
   "value": "0"
  },
  {
   "_assign": null,
   "_comments": null,
   "_liked_by": null,
   "_user_tags": null,
   "creation": "2020-06-23 11:44:38.385550",
   "default_value": null,
   "doc_type": "Quotation",
   "docstatus": 0,
   "doctype_or_field": "DocField",
   "field_name": "rounded_total",
   "idx": 0,
   "modified": "2020-06-23 11:44:38.385550",
   "modified_by": "amrutenergy@amrutenergy.com",
   "name": "Quotation-rounded_total-print_hide",
   "owner": "amrutenergy@amrutenergy.com",
   "parent": null,
   "parentfield": null,
   "parenttype": null,
   "property": "print_hide",
   "property_type": "Check",
   "row_name": null,
   "value": "0"
  },
  {
   "_assign": null,
   "_comments": null,
   "_liked_by": null,
   "_user_tags": null,
   "creation": "2020-06-23 11:44:38.255561",
   "default_value": null,
   "doc_type": "Quotation",
   "docstatus": 0,
   "doctype_or_field": "DocField",
   "field_name": "rounded_total",
   "idx": 0,
   "modified": "2020-06-23 11:44:38.255561",
   "modified_by": "amrutenergy@amrutenergy.com",
   "name": "Quotation-rounded_total-hidden",
   "owner": "amrutenergy@amrutenergy.com",
   "parent": null,
   "parentfield": null,
   "parenttype": null,
   "property": "hidden",
   "property_type": "Check",
   "row_name": null,
   "value": "0"
  },
  {
   "_assign": null,
   "_comments": null,
   "_liked_by": null,
   "_user_tags": null,
   "creation": "2020-06-23 11:44:38.121627",
   "default_value": null,
   "doc_type": "Quotation",
   "docstatus": 0,
   "doctype_or_field": "DocField",
   "field_name": "base_rounded_total",
   "idx": 0,
   "modified": "2020-06-23 11:44:38.121627",
   "modified_by": "amrutenergy@amrutenergy.com",
   "name": "Quotation-base_rounded_total-print_hide",
   "owner": "amrutenergy@amrutenergy.com",
   "parent": null,
   "parentfield": null,
   "parenttype": null,
   "property": "print_hide",
   "property_type": "Check",
   "row_name": null,
   "value": "1"
  },
  {
   "_assign": null,
   "_comments": null,
   "_liked_by": null,
   "_user_tags": null,
   "creation": "2020-06-23 11:44:37.941505",
   "default_value": null,
   "doc_type": "Quotation",
   "docstatus": 0,
   "doctype_or_field": "DocField",
   "field_name": "base_rounded_total",
   "idx": 0,
   "modified": "2020-06-23 11:44:37.941505",
   "modified_by": "amrutenergy@amrutenergy.com",
   "name": "Quotation-base_rounded_total-hidden",
   "owner": "amrutenergy@amrutenergy.com",
   "parent": null,
   "parentfield": null,
   "parenttype": null,
   "property": "hidden",
   "property_type": "Check",
   "row_name": null,
   "value": "0"
  }
 ],
 "sync_on_migrate": 1
}